{
	"schemaVersion": 1,
	"id": "${modId}-test",
	"version": "${version}",

	"name": "Simply No Shading - Test Mod",
	"authors": [
		{
			"name": "StartsMercury"
		}
	],
	"contact": {
		"homepage": "https://modrinth.com/mod/simply-no-shading",
		"sources": "https://github.com/StartsMercury/simply-no-shading",
		"issues": "https://github.com/StartsMercury/simply-no-shading/issues"
	},

	"license": "MIT",
	"icon": "assets/simply-no-shading-test/icon.png",

	"environment": "client",
	"entrypoints": {
	},
	"mixins": [
	],

	"depends": {
		"fabric-api": "*",
		"fabricloader": "*",
		"java": ">=${javaVersion}",
		"minecraft": "~${gameVersion}",
		"simply-no-shading": "*",
		"spruceui": "*"
	},
	"recommends": {
		"modmenu": "*"
	}
}
